<?xml version="1.0"?>
<mappingModel>
	<LHSMetamodel>Person.ecore</LHSMetamodel>
	<RHSMetamodel>PersonFamily.ecore</RHSMetamodel>
	<mapping>
		<LHSElement>
			<Element>Person</Element>
		</LHSElement>
		<RHSElement>
			<Element>Person</Element>
		</RHSElement>
	</mapping>
	<mapping>
		<LHSElement>
			<Element>Person.firstName</Element>
		</LHSElement>
		<RHSElement>
			<Element>Person.firstName</Element>
		</RHSElement>
	</mapping>
	<mapping>
		<LHSElement>
			<Element>Person.lastName</Element>
		</LHSElement>
		<RHSElement>
			<Element>Family</Element>
		</RHSElement>
	</mapping>
</mappingModel>
